rtl/4bitalu.v
//====================================================
// 4-bit ALU – Industry-Grade RTL
// - Lint clean
// - CDC/RDC safe (no internal clocks/resets)
// - X-propagation controlled
// - Assertion hooks included
// - UPF/CPF & DFT friendly
//====================================================

module alu_4bit (
    // Functional inputs
    input  wire [3:0] A,
    input  wire [3:0] B,
    input  wire [2:0] ALU_CTRL,

    // Functional outputs
    output reg  [3:0] RESULT,
    output reg        CARRY_OUT,
    output reg        OVERFLOW,
    output reg        ZERO,
    
    input  wire scan_enable,
    input  wire scan_in,
    output wire scan_out

);
    // Internal extended signals
    reg [4:0] sum_ext;
    reg [4:0] sub_ext;

    // ------------------------------------------------
    // Combinational ALU
    // ------------------------------------------------
    always @(*) begin
        // ---- DEFAULTS (mandatory for lint + X safety) ----
        RESULT     = 4'b0000;
        CARRY_OUT  = 1'b0;
        OVERFLOW   = 1'b0;
        ZERO       = 1'b1;      // overwritten later
        sum_ext    = 5'b00000;
        sub_ext    = 5'b00000;

        case (ALU_CTRL)

            // ADD
            3'b000: begin
                sum_ext   = {1'b0, A} + {1'b0, B};
                RESULT    = sum_ext[3:0];
                CARRY_OUT = sum_ext[4];
                OVERFLOW  = (~(A[3] ^ B[3])) & (RESULT[3] ^ A[3]);
            end

            // SUB
            3'b001: begin
                sub_ext   = {1'b0, A} + {1'b0, (~B + 4'b0001)};
                RESULT    = sub_ext[3:0];
                CARRY_OUT = sub_ext[4];
                OVERFLOW  = (A[3] ^ B[3]) & (RESULT[3] ^ A[3]);
            end

            // AND
            3'b010: RESULT = A & B;

            // OR
            3'b011: RESULT = A | B;

            // XOR
            3'b100: RESULT = A ^ B;

            // NOT A
            3'b101: RESULT = ~A;

            // PASS A
            3'b110: RESULT = A;

            // PASS B
            3'b111: RESULT = B;

            // no default needed (full opcode coverage)
        endcase

        // ZERO flag valid for all ops
        ZERO = (RESULT == 4'b0000);
    end

// Assertions go HERE (outside logic, inside module)
// ====================================================
`ifdef ASSERTIONS
// Assertions (SEC / formal / simulation)

// ALU_CTRL must never be X/Z
always @(*) begin
    assert (^ALU_CTRL !== 1'bX)
        else $error("ALU_CTRL has X/Z");
end

    // RESULT must never be X
    always @(*) begin
        assert (^RESULT !== 1'bX)
            else $error("RESULT has X");
    end
`endif

endmodule

rtl/4bitalu_tb.v
`timescale 1ns/1ps

module tb_alu_4bit;

    // DUT inputs
    reg  [3:0] A;
    reg  [3:0] B;
    reg  [2:0] ALU_CTRL;

    reg scan_enable;
    reg scan_in;

    // DUT outputs
    wire [3:0] RESULT;
    wire       CARRY_OUT;
    wire       OVERFLOW;
    wire       ZERO;
    wire       scan_out;

    // Instantiate DUT
    alu_4bit dut (
        .A(A),
        .B(B),
        .ALU_CTRL(ALU_CTRL),
        .RESULT(RESULT),
        .CARRY_OUT(CARRY_OUT),
        .OVERFLOW(OVERFLOW),
        .ZERO(ZERO),
        .scan_enable(scan_enable),
        .scan_in(scan_in),
        .scan_out(scan_out)
    );

    // Waveform dump
    initial begin
        $dumpfile("alu.vcd");
        $dumpvars(0, tb_alu_4bit);
    end

    // Task to apply stimulus
    task apply;
        input [3:0] a_in;
        input [3:0] b_in;
        input [2:0] op_in;
        begin
            A = a_in;
            B = b_in;
            ALU_CTRL = op_in;
            #10;
            $display("A=%b B=%b OP=%b | RESULT=%b CARRY=%b OVF=%b ZERO=%b",
                      A, B, ALU_CTRL, RESULT, CARRY_OUT, OVERFLOW, ZERO);
        end
    endtask

    // Test sequence
    initial begin
        // Initialize
        A = 0;
        B = 0;
        ALU_CTRL = 0;
        scan_enable = 0;
        scan_in = 0;

        #10;

        // ADD
        apply(4'd5, 4'd3, 3'b000);
        apply(4'd7, 4'd9, 3'b000);

        // SUB
        apply(4'd9, 4'd4, 3'b001);
        apply(4'd4, 4'd9, 3'b001);

        // AND
        apply(4'b1100, 4'b1010, 3'b010);

        // OR
        apply(4'b1100, 4'b1010, 3'b011);

        // XOR
        apply(4'b1100, 4'b1010, 3'b100);

        // NOT A
        apply(4'b1010, 4'b0000, 3'b101);

        // PASS A
        apply(4'b0110, 4'b0000, 3'b110);

        // PASS B
        apply(4'b0000, 4'b1111, 3'b111);

        #20;
        $display("Simulation Finished");
        $finish;
    end

endmodule

rtl/4bitalu.vcd
$date
	Mon Feb 23 20:17:00 2026
$end
$version
	Icarus Verilog
$end
$timescale
	1ps
$end
$scope module tb_alu_4bit $end
$var wire 1 ! scan_out $end
$var wire 1 " ZERO $end
$var wire 4 # RESULT [3:0] $end
$var wire 1 $ OVERFLOW $end
$var wire 1 % CARRY_OUT $end
$var reg 4 & A [3:0] $end
$var reg 3 ' ALU_CTRL [2:0] $end
$var reg 4 ( B [3:0] $end
$var reg 1 ) scan_enable $end
$var reg 1 * scan_in $end
$scope module dut $end
$var wire 4 + A [3:0] $end
$var wire 3 , ALU_CTRL [2:0] $end
$var wire 4 - B [3:0] $end
$var wire 1 ) scan_enable $end
$var wire 1 * scan_in $end
$var wire 1 ! scan_out $end
$var reg 1 % CARRY_OUT $end
$var reg 1 $ OVERFLOW $end
$var reg 4 . RESULT [3:0] $end
$var reg 1 " ZERO $end
$var reg 5 / sub_ext [4:0] $end
$var reg 5 0 sum_ext [4:0] $end
$upscope $end
$scope task apply $end
$var reg 4 1 a_in [3:0] $end
$var reg 4 2 b_in [3:0] $end
$var reg 3 3 op_in [2:0] $end
$upscope $end
$upscope $end
$enddefinitions $end
#0
$dumpvars
bx 3
bx 2
bx 1
b0 0
b0 /
b0 .
b0 -
b0 ,
b0 +
0*
0)
b0 (
b0 '
b0 &
0%
0$
b0 #
1"
0!
$end
#10000
0"
1$
b1000 #
b1000 .
b1000 0
b11 (
b11 -
b101 &
b101 +
b0 3
b11 2
b101 1
#20000
1%
b10000 0
1"
0$
b0 #
b0 .
b1001 (
b1001 -
b111 &
b111 +
b1001 2
b111 1
#30000
0"
1$
b101 #
b101 .
b10101 /
b0 0
1%
b1 '
b1 ,
b100 (
b100 -
b1001 &
b1001 +
b1 3
b100 2
b1001 1
#40000
b1011 /
0"
1$
0%
b1011 #
b1011 .
b1001 (
b1001 -
b100 &
b100 +
b1001 2
b100 1
#50000
b0 /
0"
0$
b1000 #
b1000 .
b10 '
b10 ,
b1010 (
b1010 -
b1100 &
b1100 +
b10 3
b1010 2
b1100 1
#60000
0"
b1110 #
b1110 .
b11 '
b11 ,
b11 3
#70000
0"
b110 #
b110 .
b100 '
b100 ,
b100 3
#80000
0"
b101 #
b101 .
b101 '
b101 ,
b0 (
b0 -
b1010 &
b1010 +
b101 3
b0 2
b1010 1
#90000
0"
b110 #
b110 .
b110 '
b110 ,
b110 &
b110 +
b110 3
b110 1
#100000
0"
b1111 #
b1111 .
b111 '
b111 ,
b1111 (
b1111 -
b0 &
b0 +
b111 3
b1111 2
b0 1
